sortedm2m_filter_horizontal_widget/__init__.py
sortedm2m_filter_horizontal_widget/forms.py
sortedm2m_filter_horizontal_widget/static/sortedm2m_filter_horizontal_widget/OrderedSelectBox.js
sortedm2m_filter_horizontal_widget/static/sortedm2m_filter_horizontal_widget/OrderedSelectFilter.js
sortedm2m_filter_horizontal_widget/static/sortedm2m_filter_horizontal_widget/SelectAddButton.js
sortedm2m_filter_horizontal_widget/static/sortedm2m_filter_horizontal_widget/jquery.min.js
sortedm2m_filter_horizontal_widget/static/sortedm2m_filter_horizontal_widget/widget.css
django_sortedm2m_filter_horizontal_widget-2.0.1.dist-info/LICENSE.txt
django_sortedm2m_filter_horizontal_widget-2.0.1.dist-info/METADATA
django_sortedm2m_filter_horizontal_widget-2.0.1.dist-info/WHEEL
django_sortedm2m_filter_horizontal_widget-2.0.1.dist-info/RECORD
