Metadata-Version: 2.1
Name: django-sortedm2m-filter-horizontal-widget
Version: 2.0.1
Summary: Django admin widget for Gregor Mülleggers django-sortedm2m_ library
License: BSD
Author: Sander van Leeuwen
Author-email: replytosander@gmail.com
Requires-Python: >=3.8,<4.0
Classifier: License :: Other/Proprietary License
Classifier: Programming Language :: Python :: 3
Classifier: Programming Language :: Python :: 3.8
Classifier: Programming Language :: Python :: 3.9
Classifier: Programming Language :: Python :: 3.10
Classifier: Programming Language :: Python :: 3.11
Requires-Dist: django-sortedm2m (>=3.1.1,<4.0.0)
